{
  "questionId": "186",
  "questionFrontendId": "186",
  "boundTopicId": null,
  "title": "Reverse Words in a String II",
  "titleSlug": "reverse-words-in-a-string-ii",
  "categoryTitle": "Algorithms",
  "content": "<p>Given an input string<strong><em>&nbsp;</em></strong>, reverse the string word by word.&nbsp;</p>\r\n\r\n<p><strong>Example:</strong></p>\r\n\r\n<pre>\r\n<strong>Input:  </strong>[&quot;t&quot;,&quot;h&quot;,&quot;e&quot;,&quot; &quot;,&quot;s&quot;,&quot;k&quot;,&quot;y&quot;,&quot; &quot;,&quot;i&quot;,&quot;s&quot;,&quot; &quot;,&quot;b&quot;,&quot;l&quot;,&quot;u&quot;,&quot;e&quot;]\r\n<strong>Output: </strong>[&quot;b&quot;,&quot;l&quot;,&quot;u&quot;,&quot;e&quot;,&quot; &quot;,&quot;i&quot;,&quot;s&quot;,&quot; &quot;,&quot;s&quot;,&quot;k&quot;,&quot;y&quot;,&quot; &quot;,&quot;t&quot;,&quot;h&quot;,&quot;e&quot;]</pre>\r\n\r\n<p><strong>Note:&nbsp;</strong></p>\r\n\r\n<ul>\r\n\t<li>A word is defined as a sequence of non-space characters.</li>\r\n\t<li>The input string does not contain leading or trailing spaces.</li>\r\n\t<li>The words are always separated by a single space.</li>\r\n</ul>\r\n\r\n<p><strong>Follow up:&nbsp;</strong>Could you do it <i>in-place</i> without allocating extra space?</p>\r\n",
  "isPaidOnly": true,
  "difficulty": "Medium",
  "likes": 353,
  "dislikes": 88,
  "isLiked": null,
  "similarQuestions": "[{\"title\": \"Reverse Words in a String\", \"titleSlug\": \"reverse-words-in-a-string\", \"difficulty\": \"Medium\", \"translatedTitle\": null}, {\"title\": \"Rotate Array\", \"titleSlug\": \"rotate-array\", \"difficulty\": \"Easy\", \"translatedTitle\": null}]",
  "contributors": [],
  "topicTags": [
    {
      "name": "String",
      "slug": "string"
    }
  ],
  "companyTagStats": "{\"3\": [{\"taggedByAdmin\": false, \"name\": \"Facebook\", \"slug\": \"facebook\", \"timesEncountered\": 2}, {\"taggedByAdmin\": true, \"name\": \"Amazon\", \"slug\": \"amazon\", \"timesEncountered\": 0}, {\"taggedByAdmin\": true, \"name\": \"Uber\", \"slug\": \"uber\", \"timesEncountered\": 0}], \"1\": [{\"taggedByAdmin\": true, \"name\": \"Microsoft\", \"slug\": \"microsoft\", \"timesEncountered\": 3}], \"2\": []}",
  "codeSnippets": [
    {
      "lang": "C++",
      "code": "class Solution {\npublic:\n    void reverseWords(vector<char>& s) {\n        \n    }\n};"
    },
    {
      "lang": "Java",
      "code": "class Solution {\n    public void reverseWords(char[] s) {\n        \n    }\n}"
    },
    {
      "lang": "Python",
      "code": "class Solution(object):\n    def reverseWords(self, s):\n        \"\"\"\n        :type s: List[str]\n        :rtype: None Do not return anything, modify s in-place instead.\n        \"\"\"\n        "
    },
    {
      "lang": "Python3",
      "code": "class Solution:\n    def reverseWords(self, s: List[str]) -> None:\n        \"\"\"\n        Do not return anything, modify s in-place instead.\n        \"\"\"\n        "
    },
    {
      "lang": "C",
      "code": "\n\nvoid reverseWords(char* s, int sSize){\n\n}\n\n"
    },
    {
      "lang": "C#",
      "code": "public class Solution {\n    public void ReverseWords(char[] s) {\n        \n    }\n}"
    },
    {
      "lang": "JavaScript",
      "code": "/**\n * @param {character[]} s\n * @return {void} Do not return anything, modify s in-place instead.\n */\nvar reverseWords = function(s) {\n    \n};"
    },
    {
      "lang": "Ruby",
      "code": "# @param {Character[]} s\n# @return {Void} Do not return anything, modify s in-place instead.\ndef reverse_words(s)\n    \nend"
    },
    {
      "lang": "Swift",
      "code": "class Solution {\n    func reverseWords(_ s: inout [Character]) {\n        \n    }\n}"
    },
    {
      "lang": "Go",
      "code": "func reverseWords(s []byte)  {\n    \n}"
    },
    {
      "lang": "Scala",
      "code": "object Solution {\n    def reverseWords(s: Array[Char]): Unit = {\n        \n    }\n}"
    },
    {
      "lang": "Kotlin",
      "code": "class Solution {\n    fun reverseWords(s: CharArray): Unit {\n        \n    }\n}"
    },
    {
      "lang": "Rust",
      "code": "impl Solution {\n    pub fn reverse_words(s: &mut Vec<char>) {\n        \n    }\n}"
    },
    {
      "lang": "PHP",
      "code": "class Solution {\n\n    /**\n     * @param String[] $s\n     * @return NULL\n     */\n    function reverseWords(&$s) {\n        \n    }\n}"
    }
  ],
  "stats": "{\"totalAccepted\": \"76.5K\", \"totalSubmission\": \"188.5K\", \"totalAcceptedRaw\": 76497, \"totalSubmissionRaw\": 188502, \"acRate\": \"40.6%\"}",
  "hints": [],
  "solution": null,
  "status": null,
  "sampleTestCase": "[\"t\",\"h\",\"e\",\" \",\"s\",\"k\",\"y\",\" \",\"i\",\"s\",\" \",\"b\",\"l\",\"u\",\"e\"]",
  "metaData": "{\n  \"name\": \"reverseWords\",\n  \"params\": [\n    {\n      \"name\": \"s\",\n      \"type\": \"character[]\"\n    }\n  ],\n  \"return\": {\n    \"type\": \"void\"\n  },\n  \"output\": {\n    \"paramindex\": 0\n  }\n}",
  "judgerAvailable": true,
  "judgeType": "large",
  "mysqlSchemas": [],
  "enableRunCode": true,
  "enableTestMode": false,
  "libraryUrl": null
}
